taileff/__init__.py
taileff/__main__.py
taileff/core.py
taileff-0.1.0.dist-info/DESCRIPTION.rst
taileff-0.1.0.dist-info/entry_points.txt
taileff-0.1.0.dist-info/METADATA
taileff-0.1.0.dist-info/metadata.json
taileff-0.1.0.dist-info/RECORD
taileff-0.1.0.dist-info/top_level.txt
taileff-0.1.0.dist-info/WHEEL
